src/__init__.py
src/minus/__init__.py
src/minus/minus_with_one.py
src/sum/__init__.py
src/sum/sum_with_one.py
jira_test-0.0.1.dist-info/METADATA
jira_test-0.0.1.dist-info/WHEEL
jira_test-0.0.1.dist-info/entry_points.txt
jira_test-0.0.1.dist-info/top_level.txt
jira_test-0.0.1.dist-info/RECORD
